antp/__init__.py
antp/__main__.py
antp/processor.py
antp/template.py
antp/filters/__init__.py
antp/filters/fromjson.py
antp-0.1.1.dist-info/METADATA
antp-0.1.1.dist-info/WHEEL
antp-0.1.1.dist-info/top_level.txt
antp-0.1.1.dist-info/RECORD
