Metadata-Version: 2.1
Name: antp
Version: 0.1.1
Summary: Python Template Processor for Jinja templates
Author-email: Antti Nilsson <muut.py@antion.fi>
Classifier: Programming Language :: Python :: 3
Classifier: License :: OSI Approved :: MIT License
Classifier: Operating System :: OS Independent
Requires-Python: >=3.7
Requires-Dist: Jinja2
Requires-Dist: anoptions
